nonebot_plugin_Imagelabels/Download.py
nonebot_plugin_Imagelabels/__init__.py
nonebot_plugin_Imagelabels/get_video_group.py
nonebot_plugin_Imagelabels/recover.py
nonebot_plugin_Imagelabels-1.0.0.dist-info/LICENSE.txt
nonebot_plugin_Imagelabels-1.0.0.dist-info/METADATA
nonebot_plugin_Imagelabels-1.0.0.dist-info/WHEEL
nonebot_plugin_Imagelabels-1.0.0.dist-info/top_level.txt
nonebot_plugin_Imagelabels-1.0.0.dist-info/RECORD
