Metadata-Version: 2.1
Name: nonebot-plugin-Imagelabels
Version: 1.0.0
Summary: 基于yolov5实现的图像标注的Nonebot插件
Home-page: https://github.com/istrashguy/nonebot_plugin_Imagelabels
Author: Shen_heart
Author-email: 692644718@qq.com
Maintainer: Heart
Maintainer-email: qsu666947@163.com
License: MIT
Platform: all
Classifier: Development Status :: 4 - Beta
Classifier: Operating System :: OS Independent
Classifier: Intended Audience :: Developers
Classifier: License :: OSI Approved :: MIT License
Classifier: Programming Language :: Python
Classifier: Programming Language :: Python :: Implementation
Classifier: Programming Language :: Python :: 3.8
Classifier: Programming Language :: Python :: 3.9
Classifier: Programming Language :: Python :: 3.10
Classifier: Topic :: Software Development :: Libraries
Requires-Python: >=3.8
License-File: LICENSE.txt
Requires-Dist: nonebot2 (<3.0.0,>=2.0.0rc1)
Requires-Dist: nonebot-adapter-onebot
Requires-Dist: matplotlib (>=3.2.2)
Requires-Dist: numpy (>=1.18.5)
Requires-Dist: opencv-python (>=4.1.2)
Requires-Dist: Pillow (>=7.1.2)
Requires-Dist: PyYAML (>=5.3.1)
Requires-Dist: requests (>=2.23.0)
Requires-Dist: scipy (>=1.4.1)
Requires-Dist: torch (>=1.7.0)
Requires-Dist: torchvision (>=0.8.1)
Requires-Dist: tqdm (>=4.41.0)
Requires-Dist: tensorboard (>=2.4.1)
Requires-Dist: pandas (>=1.1.4)
Requires-Dist: seaborn (>=0.11.0)
Requires-Dist: httpx
